{
  "generator-jhipster": {
    "applicationType": "microservice",
    "gitCompany": "",
    "baseName": "SmsBroadcast",
    "packageName": "com.ft",
    "packageFolder": "com/ft",
    "serverPort": 8081,
    "serviceDiscoveryType": "consul",
    "authenticationType": "jwt",
    "uaaBaseName": "../uaa",
    "cacheProvider": "hazelcast",
    "enableHibernateCache": true,
    "websocket": false,
    "databaseType": "sql",
    "devDatabaseType": "postgresql",
    "prodDatabaseType": "postgresql",
    "searchEngine": false,
    "enableSwaggerCodegen": "true",
    "messageBroker": false,
    "buildTool": "maven",
    "useSass": true,
    "clientPackageManager": "npm",
    "testFrameworks": [],
    "enableTranslation": true,
    "nativeLanguage": "en",
    "languages": ["en", "vi"],
    "clientFramework": "angularX",
    "jhiPrefix": "jhi",
    "jhipsterVersion": "6.8.0",
    "jwtSecretKey": "MjkzMWViOGZmZjNlYTQ1YWFhYWUwZGEwNTcxOTk1YjQwYzNkMDE5NzE3NTZjMzg1NWY5ODIxM2EzNWUyMTAwZTlkODc1NDYwOTRlOGE3NjQyMDRhZGI5OWNjNjFhYzY3M2U4YTk4ZTI2NWY4OGI0ZjVlYTllYThiNTllMmZlZTk=",
    "embeddableLaunchScript": false,
    "creationTimestamp": 1588559162639,
    "entitySuffix": "",
    "dtoSuffix": "DTO",
    "otherModules": [],
    "blueprints": [],
    "skipClient": true,
    "skipUserManagement": true
  },
  "git-provider": "GitHub",
  "git-company": "foxtechvn",
  "repository-name": "vascloud-sms-broadcast"
}
